{
    "info": {
        "id": 6700668,
        "joined_time": "2025-08-13T18:42:48.476305Z",
        "started_event": 1,
        "favourite_team": 17,
        "player_first_name": "Scott",
        "player_last_name": "Mason",
        "player_region_id": 243,
        "player_region_name": "Scotland",
        "player_region_iso_code_short": "S1",
        "player_region_iso_code_long": "SCO",
        "years_active": 0,
        "summary_overall_points": 193,
        "summary_overall_rank": 19,
        "summary_event_points": 91,
        "summary_event_rank": 33516,
        "current_event": 2,
        "leagues": {
            "classic": [
                {
                    "id": 17,
                    "name": "Sunderland",
                    "short_name": "team-17",
                    "created": "2025-07-20T23:14:28.608486Z",
                    "closed": false,
                    "rank": null,
                    "max_entries": null,
                    "league_type": "s",
                    "scoring": "c",
                    "admin_entry": null,
                    "start_event": 1,
                    "entry_can_leave": false,
                    "entry_can_admin": false,
                    "entry_can_invite": false,
                    "has_cup": true,
                    "cup_league": null,
                    "cup_qualified": null,
                    "rank_count": 68065,
                    "entry_percentile_rank": 1,
                    "active_phases": [
                        {
                            "phase": 1,
                            "rank": 1,
                            "last_rank": 31,
                            "rank_sort": 1,
                            "total": 193,
                            "league_id": 17,
                            "rank_count": 68065,
                            "entry_percentile_rank": 1
                        },
                        {
                            "phase": 2,
                            "rank": 1,
                            "last_rank": 31,
                            "rank_sort": 1,
                            "total": 193,
                            "league_id": 17,
                            "rank_count": 68065,
                            "entry_percentile_rank": 1
                        }
                    ],
                    "entry_rank": 1,
                    "entry_last_rank": 31
                },
                {
                    "id": 263,
                    "name": "Scotland",
                    "short_name": "region-243",
                    "created": "2025-07-20T23:14:33.034163Z",
                    "closed": false,
                    "rank": null,
                    "max_entries": null,
                    "league_type": "s",
                    "scoring": "c",
                    "admin_entry": null,
                    "start_event": 1,
                    "entry_can_leave": false,
                    "entry_can_admin": false,
                    "entry_can_invite": false,
                    "has_cup": true,
                    "cup_league": null,
                    "cup_qualified": null,
                    "rank_count": 180136,
                    "entry_percentile_rank": 1,
                    "active_phases": [
                        {
                            "phase": 1,
                            "rank": 1,
                            "last_rank": 23,
                            "rank_sort": 1,
                            "total": 193,
                            "league_id": 263,
                            "rank_count": 180136,
                            "entry_percentile_rank": 1
                        },
                        {
                            "phase": 2,
                            "rank": 1,
                            "last_rank": 23,
                            "rank_sort": 1,
                            "total": 193,
                            "league_id": 263,
                            "rank_count": 180136,
                            "entry_percentile_rank": 1
                        }
                    ],
                    "entry_rank": 1,
                    "entry_last_rank": 23
                },
                {
                    "id": 276,
                    "name": "Gameweek 1",
                    "short_name": "event-1",
                    "created": "2025-07-20T23:14:33.264422Z",
                    "closed": false,
                    "rank": null,
                    "max_entries": null,
                    "league_type": "s",
                    "scoring": "c",
                    "admin_entry": null,
                    "start_event": 1,
                    "entry_can_leave": false,
                    "entry_can_admin": false,
                    "entry_can_invite": false,
                    "has_cup": false,
                    "cup_league": null,
                    "cup_qualified": null,
                    "rank_count": 9462215,
                    "entry_percentile_rank": 1,
                    "active_phases": [
                        {
                            "phase": 1,
                            "rank": 19,
                            "last_rank": 1829,
                            "rank_sort": 19,
                            "total": 193,
                            "league_id": 276,
                            "rank_count": 9462215,
                            "entry_percentile_rank": 1
                        },
                        {
                            "phase": 2,
                            "rank": 19,
                            "last_rank": 1829,
                            "rank_sort": 19,
                            "total": 193,
                            "league_id": 276,
                            "rank_count": 9462198,
                            "entry_percentile_rank": 1
                        }
                    ],
                    "entry_rank": 19,
                    "entry_last_rank": 1829
                },
                {
                    "id": 314,
                    "name": "Overall",
                    "short_name": "overall",
                    "created": "2025-07-20T23:14:33.933835Z",
                    "closed": false,
                    "rank": null,
                    "max_entries": null,
                    "league_type": "s",
                    "scoring": "c",
                    "admin_entry": null,
                    "start_event": 1,
                    "entry_can_leave": false,
                    "entry_can_admin": false,
                    "entry_can_invite": false,
                    "has_cup": true,
                    "cup_league": null,
                    "cup_qualified": null,
                    "rank_count": 10753829,
                    "entry_percentile_rank": 1,
                    "active_phases": [
                        {
                            "phase": 1,
                            "rank": 19,
                            "last_rank": 1829,
                            "rank_sort": 19,
                            "total": 193,
                            "league_id": 314,
                            "rank_count": 10753829,
                            "entry_percentile_rank": 1
                        },
                        {
                            "phase": 2,
                            "rank": 19,
                            "last_rank": 1829,
                            "rank_sort": 19,
                            "total": 193,
                            "league_id": 314,
                            "rank_count": 10754799,
                            "entry_percentile_rank": 1
                        }
                    ],
                    "entry_rank": 19,
                    "entry_last_rank": 1829
                },
                {
                    "id": 321,
                    "name": "Sky Sports League",
                    "short_name": "brd-skysports",
                    "created": "2025-07-20T23:14:34.060791Z",
                    "closed": false,
                    "rank": null,
                    "max_entries": null,
                    "league_type": "s",
                    "scoring": "c",
                    "admin_entry": null,
                    "start_event": 1,
                    "entry_can_leave": false,
                    "entry_can_admin": false,
                    "entry_can_invite": false,
                    "has_cup": true,
                    "cup_league": null,
                    "cup_qualified": null,
                    "rank_count": 3476587,
                    "entry_percentile_rank": 1,
                    "active_phases": [
                        {
                            "phase": 1,
                            "rank": 3,
                            "last_rank": 487,
                            "rank_sort": 3,
                            "total": 193,
                            "league_id": 321,
                            "rank_count": 3476587,
                            "entry_percentile_rank": 1
                        },
                        {
                            "phase": 2,
                            "rank": 3,
                            "last_rank": 487,
                            "rank_sort": 3,
                            "total": 193,
                            "league_id": 321,
                            "rank_count": 3476266,
                            "entry_percentile_rank": 1
                        }
                    ],
                    "entry_rank": 3,
                    "entry_last_rank": 487
                },
                {
                    "id": 333,
                    "name": "Second Chance",
                    "short_name": "sc",
                    "created": "2025-07-20T23:14:34.276586Z",
                    "closed": false,
                    "rank": null,
                    "max_entries": null,
                    "league_type": "s",
                    "scoring": "c",
                    "admin_entry": null,
                    "start_event": 21,
                    "entry_can_leave": false,
                    "entry_can_admin": false,
                    "entry_can_invite": false,
                    "has_cup": false,
                    "cup_league": null,
                    "cup_qualified": null,
                    "rank_count": null,
                    "entry_percentile_rank": null,
                    "active_phases": [
                        {
                            "phase": 1,
                            "rank": 0,
                            "last_rank": 0,
                            "rank_sort": 0,
                            "total": 0,
                            "league_id": 333,
                            "rank_count": null,
                            "entry_percentile_rank": null
                        },
                        {
                            "phase": 2,
                            "rank": 0,
                            "last_rank": 0,
                            "rank_sort": 0,
                            "total": 0,
                            "league_id": 333,
                            "rank_count": null,
                            "entry_percentile_rank": null
                        }
                    ],
                    "entry_rank": 0,
                    "entry_last_rank": 0
                },
                {
                    "id": 248502,
                    "name": "Anti FPL League 25/26",
                    "short_name": null,
                    "created": "2025-07-23T09:18:45.420585Z",
                    "closed": false,
                    "rank": null,
                    "max_entries": null,
                    "league_type": "x",
                    "scoring": "c",
                    "admin_entry": 1117518,
                    "start_event": 1,
                    "entry_can_leave": true,
                    "entry_can_admin": false,
                    "entry_can_invite": false,
                    "has_cup": true,
                    "cup_league": null,
                    "cup_qualified": null,
                    "rank_count": 163,
                    "entry_percentile_rank": 1,
                    "active_phases": [
                        {
                            "phase": 1,
                            "rank": 1,
                            "last_rank": 1,
                            "rank_sort": 1,
                            "total": 193,
                            "league_id": 248502,
                            "rank_count": 163,
                            "entry_percentile_rank": 1
                        },
                        {
                            "phase": 2,
                            "rank": 1,
                            "last_rank": 1,
                            "rank_sort": 1,
                            "total": 193,
                            "league_id": 248502,
                            "rank_count": 163,
                            "entry_percentile_rank": 1
                        }
                    ],
                    "entry_rank": 1,
                    "entry_last_rank": 1
                }
            ],
            "h2h": [],
            "cup": {
                "matches": [],
                "status": {
                    "qualification_event": null,
                    "qualification_numbers": null,
                    "qualification_rank": null,
                    "qualification_state": null
                },
                "cup_league": null
            },
            "cup_matches": []
        },
        "name": "Bad2dabone FC",
        "name_change_blocked": false,
        "entered_events": [
            1,
            2
        ],
        "kit": null,
        "last_deadline_bank": 35,
        "last_deadline_value": 1002,
        "last_deadline_total_transfers": 1,
        "club_badge_src": null
    },
    "history": {
        "current": [
            {
                "event": 1,
                "points": 102,
                "total_points": 102,
                "rank": 1829,
                "rank_sort": 2196,
                "overall_rank": 1829,
                "percentile_rank": 1,
                "bank": 120,
                "value": 1000,
                "event_transfers": 0,
                "event_transfers_cost": 0,
                "points_on_bench": 0
            },
            {
                "event": 2,
                "points": 91,
                "total_points": 193,
                "rank": 33516,
                "rank_sort": 34804,
                "overall_rank": 19,
                "percentile_rank": 1,
                "bank": 35,
                "value": 1002,
                "event_transfers": 1,
                "event_transfers_cost": 0,
                "points_on_bench": 11
            }
        ],
        "past": [],
        "chips": [
            {
                "name": "bboost",
                "time": "2025-08-14T22:49:53.640438Z",
                "event": 1
            },
            {
                "name": "3xc",
                "time": "2025-08-19T11:08:13.555387Z",
                "event": 2
            }
        ]
    },
    "gw_picks": {
        "active_chip": "3xc",
        "automatic_subs": [],
        "entry_history": {
            "event": 2,
            "points": 91,
            "total_points": 193,
            "rank": 33516,
            "rank_sort": 34804,
            "overall_rank": 19,
            "percentile_rank": 1,
            "bank": 35,
            "value": 1002,
            "event_transfers": 1,
            "event_transfers_cost": 0,
            "points_on_bench": 11
        },
        "picks": [
            {
                "element": 1,
                "position": 1,
                "multiplier": 1,
                "is_captain": false,
                "is_vice_captain": false,
                "element_type": 1
            },
            {
                "element": 151,
                "position": 2,
                "multiplier": 1,
                "is_captain": false,
                "is_vice_captain": false,
                "element_type": 2
            },
            {
                "element": 444,
                "position": 3,
                "multiplier": 1,
                "is_captain": false,
                "is_vice_captain": false,
                "element_type": 2
            },
            {
                "element": 6,
                "position": 4,
                "multiplier": 1,
                "is_captain": false,
                "is_vice_captain": false,
                "element_type": 2
            },
            {
                "element": 157,
                "position": 5,
                "multiplier": 1,
                "is_captain": false,
                "is_vice_captain": false,
                "element_type": 3
            },
            {
                "element": 236,
                "position": 6,
                "multiplier": 1,
                "is_captain": false,
                "is_vice_captain": false,
                "element_type": 3
            },
            {
                "element": 82,
                "position": 7,
                "multiplier": 1,
                "is_captain": false,
                "is_vice_captain": false,
                "element_type": 3
            },
            {
                "element": 21,
                "position": 8,
                "multiplier": 1,
                "is_captain": false,
                "is_vice_captain": false,
                "element_type": 3
            },
            {
                "element": 430,
                "position": 9,
                "multiplier": 1,
                "is_captain": false,
                "is_vice_captain": false,
                "element_type": 4
            },
            {
                "element": 597,
                "position": 10,
                "multiplier": 1,
                "is_captain": false,
                "is_vice_captain": true,
                "element_type": 4
            },
            {
                "element": 249,
                "position": 11,
                "multiplier": 3,
                "is_captain": true,
                "is_vice_captain": false,
                "element_type": 4
            },
            {
                "element": 139,
                "position": 12,
                "multiplier": 0,
                "is_captain": false,
                "is_vice_captain": false,
                "element_type": 1
            },
            {
                "element": 48,
                "position": 13,
                "multiplier": 0,
                "is_captain": false,
                "is_vice_captain": false,
                "element_type": 3
            },
            {
                "element": 569,
                "position": 14,
                "multiplier": 0,
                "is_captain": false,
                "is_vice_captain": false,
                "element_type": 2
            },
            {
                "element": 474,
                "position": 15,
                "multiplier": 0,
                "is_captain": false,
                "is_vice_captain": false,
                "element_type": 2
            }
        ]
    }
}